{"__symbolic":"module","version":3,"metadata":{"ClarityModule":{"__symbolic":"class","decorators":[{"__symbolic":"call","expression":{"__symbolic":"reference","module":"@angular/core","name":"NgModule"},"arguments":[{"imports":[{"__symbolic":"reference","module":"@angular/common","name":"CommonModule"},{"__symbolic":"reference","module":"@angular/forms","name":"FormsModule"}],"declarations":[],"exports":[]}]}],"members":{},"statics":{"forRoot":{"__symbolic":"function","parameters":[],"value":{"ngModule":{"__symbolic":"reference","name":"ClarityModule"},"providers":[{"__symbolic":"reference","name":"ɵa"}]}},"forChild":{"__symbolic":"function","parameters":[],"value":{"ngModule":{"__symbolic":"reference","name":"ClarityModule"},"providers":[]}}}},"DropDown":{"__symbolic":"class","extends":{"__symbolic":"reference","name":"ɵb"},"members":{"__ctor__":[{"__symbolic":"constructor","parameters":[{"__symbolic":"reference","name":"any"},null]}],"selectAll":[{"__symbolic":"method"}],"onTextChanged":[{"__symbolic":"method"}],"onIsDroppedDownChanging":[{"__symbolic":"method"}],"onIsDroppedDownChanged":[{"__symbolic":"method"}],"onGotFocus":[{"__symbolic":"method"}],"onLostFocus":[{"__symbolic":"method"}],"containsFocus":[{"__symbolic":"method"}],"dispose":[{"__symbolic":"method"}],"refresh":[{"__symbolic":"method"}],"_handleResize":[{"__symbolic":"method"}],"_expandSelection":[{"__symbolic":"method"}],"_getCharType":[{"__symbolic":"method"}],"_keydown":[{"__symbolic":"method"}],"_btnclick":[{"__symbolic":"method"}],"_setText":[{"__symbolic":"method"}],"_updateBtn":[{"__symbolic":"method"}],"_createDropDown":[{"__symbolic":"method"}],"_commitText":[{"__symbolic":"method"}],"_updateDropDown":[{"__symbolic":"method"}]},"statics":{"controlTemplate":"<div style=\"position:relative\" class=\"wj-template\"><div class=\"wj-input\"><div class=\"wj-input-group wj-input-btn-visible\"><input wj-part=\"input\" type=\"text\" class=\"wj-form-control\" /><span wj-part=\"btn\" class=\"wj-input-group-btn\" tabindex=\"-1\"><button class=\"wj-btn wj-btn-default\" type=\"button\" tabindex=\"-1\"><span class=\"wj-glyph-down\"></span></button></span></div></div><div wj-part=\"dropdown\" class=\"wj-content wj-dropdown-panel\" style=\"display:none;position:absolute;z-index:100;width:auto\"></div></div>"}},"ComboBox":{"__symbolic":"class","extends":{"__symbolic":"reference","name":"DropDown"},"members":{"__ctor__":[{"__symbolic":"constructor","parameters":[{"__symbolic":"reference","name":"any"},null]}],"getDisplayText":[{"__symbolic":"method"}],"onSelectedIndexChanged":[{"__symbolic":"method"}],"indexOf":[{"__symbolic":"method"}],"onLostFocus":[{"__symbolic":"method"}],"onIsDroppedDownChanging":[{"__symbolic":"method"}],"onIsDroppedDownChanged":[{"__symbolic":"method"}],"_updateBtn":[{"__symbolic":"method"}],"_createDropDown":[{"__symbolic":"method"}],"_setText":[{"__symbolic":"method"}],"_findNext":[{"__symbolic":"method"}],"_keydown":[{"__symbolic":"method"}],"_setSelectionRange":[{"__symbolic":"method"}],"_getSelStart":[{"__symbolic":"method"}]}},"ɵa":{"__symbolic":"class","decorators":[{"__symbolic":"call","expression":{"__symbolic":"reference","module":"@angular/core","name":"Injectable"}}],"members":{"__ctor__":[{"__symbolic":"constructor"}],"registerNav":[{"__symbolic":"method"}],"isNavRegistered":[{"__symbolic":"method"}],"unregisterNav":[{"__symbolic":"method"}],"sendControlMessage":[{"__symbolic":"method"}],"closeAllNavs":[{"__symbolic":"method"}]}},"ɵb":{"__symbolic":"class","members":{"__ctor__":[{"__symbolic":"constructor","parameters":[{"__symbolic":"reference","name":"any"},null,null]}],"getTemplate":[{"__symbolic":"method"}],"applyTemplate":[{"__symbolic":"method"}],"dispose":[{"__symbolic":"method"}],"focus":[{"__symbolic":"method"}],"containsFocus":[{"__symbolic":"method"}],"invalidate":[{"__symbolic":"method"}],"refresh":[{"__symbolic":"method"}],"beginUpdate":[{"__symbolic":"method"}],"endUpdate":[{"__symbolic":"method"}],"deferUpdate":[{"__symbolic":"method"}],"initialize":[{"__symbolic":"method"}],"addEventListener":[{"__symbolic":"method"}],"removeEventListener":[{"__symbolic":"method"}],"onGotFocus":[{"__symbolic":"method"}],"onLostFocus":[{"__symbolic":"method"}],"_handleResize":[{"__symbolic":"method"}],"_updateFocusState":[{"__symbolic":"method"}],"_handleTouchStart":[{"__symbolic":"method"}],"_handleTouchEnd":[{"__symbolic":"method"}],"_handleDisabled":[{"__symbolic":"method"}],"_replaceWithDiv":[{"__symbolic":"method"}],"_copyOriginalAttributes":[{"__symbolic":"method"}]},"statics":{"_DATA_KEY":"wj-Control","_REFRESH_INTERVAL":10,"_wme":{"__symbolic":"error","message":"Variable not initialized","line":33,"character":19},"_touching":{"__symbolic":"error","message":"Variable not initialized","line":34,"character":11}}}},"origins":{"ClarityModule":"./src/clarity-light/clarity.module","DropDown":"./src/clarity-light/wigfrid/components/DropDown/DropDown","ComboBox":"./src/clarity-light/wigfrid/components/ComboBox/ComboBox","ɵa":"./src/clarity-light/nav/clrResponsiveNavigationService","ɵb":"./src/clarity-light/wigfrid/components/Control"},"importAs":"ui-components-light"}